<?xml version="1.0" encoding="UTF-8"?>
<Window  size="150,780">
  <Font id="140010" name="微软雅黑" size="14" bold="false" underline="true"/>
  <VerticalLayout name="bk" bkcolor="#FF474747" inset="0,5,0,0">

    <HorizontalLayout name="top" pos="0,0,0,30" inset="12,0,3,0">
      <Label  name="type_name"  maxwidth="114" endellipsis="true" pos="0,0,60,30" textcolor="FFFFFFFF" text="课件详情"/>
      <Control  width="8" />
      <Label  name="type_count" pos="0,0,30,30" textcolor="FFDCF000" text="0"/>
      <Label  name="type_count_empty" textcolor="FFDCF000" text=""/>
      <Button name="close" pos="0,0,30,30" bkimage="file='RightBar/Explorer/btn_close.png' source='0,0,30,30'" hotimage="file='RightBar/Explorer/btn_close.png' source='30,0,60,30'" pushedimage="file='RightBar/Explorer/btn_close.png' source='60,0,90,30'"/>
    </HorizontalLayout>

    <VerticalLayout  inset="12,0,12,0" height="1">
      <Control  bkcolor="#FF595959"/>
    </VerticalLayout>

    <Container name="body">

      <SliderTabLayoutUI name="sliderTabLayout" selectedid="1" >
        <VerticalLayout name="loginContent">
        </VerticalLayout>
        <VerticalLayout>

          <VerticalLayout name="content" inset="0,10,0,0" childpadding="25" vscrollbar="true" vscrollbarstyle="thumbnormalimage=&quot;file='RightBar/Explorer/scroll_normal.png' corner='8,12,8,12'&quot; thumbhotimage=&quot;file='RightBar/Explorer/scroll_hover.png' corner='8,12,8,12'&quot; thumbpushedimage=&quot;file='RightBar/Explorer/scroll_pushed.png' corner='8,12,8,12'&quot; showbutton1=&quot;false&quot; showbutton2=&quot;false&quot; width=&quot;18&quot; ">
          </VerticalLayout>

          <VerticalLayout name="lay_see_more" height="30" visible="false">
            <Control />
            <HorizontalLayout height="20">
              <Control />
              <Button width="70" name="btn_see_more" text="查看更多..." textcolor="#FF0FB0B6" align="center"/>
              <Control />
            </HorizontalLayout>
            <Control />
          </VerticalLayout>

        </VerticalLayout>

        <VerticalLayout name="changePasswordContent">
        </VerticalLayout>
        <VerticalLayout name="getBackPwdContent">
        </VerticalLayout>
        <VerticalLayout name="cloudAssetscontent">
        </VerticalLayout>
        <VerticalLayout name="dbankAssetscontent">
        </VerticalLayout>
        <VerticalLayout name="searchcontent">
        </VerticalLayout>
        <VerticalLayout name="uploadcontent">
        </VerticalLayout>
      </SliderTabLayoutUI>

      <VerticalLayout  bkcolor="#FF474747" name="netless" visible="false">
        <Control name="none1"/>
        <HorizontalLayout>
          <Control />
          <Control name="icon"  pos="0,0,139,133" bkimage="RightBar/Explorer/netless_icon.png"/>
          <Control />
        </HorizontalLayout>
        <HorizontalLayout>
          <Control />
          <Button name="refresh"  pos="0,0,90,35" text="刷新" bkcolor="#FF11B0B6" hotbkcolor="#FF21d0d6" textcolor="#FFFFFFFF"/>
          <Control />
        </HorizontalLayout>
        <Control />
      </VerticalLayout>

      <VerticalLayout bkimage="file='RightBar/item/btn_bk_normal.png'  corner='1,1,1,1'" name="mask" visible="false">
        <Control />
        <HorizontalLayout name="toolbar" height="35">
          <Control />
          <GifAnim name="loading" pos="0,0,36,36" bkimage="RightBar/item/item_loading.gif" auto="true"/>
          <Control />
        </HorizontalLayout>
        <Label name="loading_tip"  text="加载中..." padding="0,4,0,0" textcolor="#FFFFFFFF" align="center" />
        <Control />
      </VerticalLayout>

    </Container>

  </VerticalLayout>
</Window>